autogenui/__init__.py
autogenui/cli.py
autogenui/datamodel.py
autogenui/flow.py
autogenui/manager.py
autogenui/utils.py
autogenui/version.py
autogenui/web/__init__.py
autogenui/web/app.py
autogenui/web/ui/404.html
autogenui/web/ui/favicon.ico
autogenui/web/ui/index.html
autogenui/web/ui/index.txt
autogenui/web/ui/next.svg
autogenui/web/ui/playground.html
autogenui/web/ui/playground.txt
autogenui/web/ui/vercel.svg
autogenui/web/ui/_next/static/NWej-JnyFhNrdwEtMGlHt/_buildManifest.js
autogenui/web/ui/_next/static/NWej-JnyFhNrdwEtMGlHt/_ssgManifest.js
autogenui/web/ui/_next/static/chunks/300-c1afed695231dd49.js
autogenui/web/ui/_next/static/chunks/472-f339164c55cba059.js
autogenui/web/ui/_next/static/chunks/689-fb905c9362567d48.js
autogenui/web/ui/_next/static/chunks/900-4a297f6319ba0e81.js
autogenui/web/ui/_next/static/chunks/980-d995cbebfdb04c27.js
autogenui/web/ui/_next/static/chunks/c37d3baf-51f830ddfae193ff.js
autogenui/web/ui/_next/static/chunks/fd9d1056-d92e438e9625d7cd.js
autogenui/web/ui/_next/static/chunks/framework-43665103d101a22d.js
autogenui/web/ui/_next/static/chunks/main-app-3f66fab784df7a8d.js
autogenui/web/ui/_next/static/chunks/main-c059cd8f0b590512.js
autogenui/web/ui/_next/static/chunks/polyfills-c67a75d1b6f99dc8.js
autogenui/web/ui/_next/static/chunks/webpack-73779742c80db59b.js
autogenui/web/ui/_next/static/chunks/app/_not-found-557909583c0e678e.js
autogenui/web/ui/_next/static/chunks/app/layout-0fddb05b38ce9976.js
autogenui/web/ui/_next/static/chunks/app/page-ed87babd88448a1f.js
autogenui/web/ui/_next/static/chunks/app/playground/page-8f80b36c1c0a9d5b.js
autogenui/web/ui/_next/static/chunks/pages/_app-451d704a741dc8a8.js
autogenui/web/ui/_next/static/chunks/pages/_error-d6885ef27f2c5e3d.js
autogenui/web/ui/_next/static/css/33645606b33eb2d3.css
autogenui/web/ui/_next/static/css/b4846eed11c4725f.css
autogenui-0.0.4a0.dist-info/LICENSE
autogenui-0.0.4a0.dist-info/METADATA
autogenui-0.0.4a0.dist-info/WHEEL
autogenui-0.0.4a0.dist-info/entry_points.txt
autogenui-0.0.4a0.dist-info/top_level.txt
autogenui-0.0.4a0.dist-info/RECORD
