Metadata-Version: 2.1
Name: autogenui
Version: 0.0.4a0
Summary: autogen ui: a ui interface for the autogen library 
Author-email: Victor Dibia <victor.dibia@gmail.com>
License: MIT License
Project-URL: Homepage, https://github.com/victordibia/autogenui
Project-URL: Bug Tracker, https://github.com/victordibia/autogenui/issues
Classifier: Programming Language :: Python :: 3
Classifier: License :: OSI Approved :: MIT License
Classifier: Operating System :: OS Independent
Requires-Python: >=3.9
License-File: LICENSE
Requires-Dist: pydantic
Requires-Dist: fastapi
Requires-Dist: typer
Requires-Dist: uvicorn
Requires-Dist: pyautogen
Provides-Extra: web
Requires-Dist: fastapi ; extra == 'web'
Requires-Dist: uvicorn ; extra == 'web'
